qa.py
routing.py
smart_answer_core/__init__.py
smart_answer_core/base_tool.py
smart_answer_core/logger.py
smart_answer_core/sample_tools.py
smart_answer_core/smart_answer.py
smart_answer_core/tool_example.py
smart_answer_core/tool_selector.py
smart_answer_core/util.py
smart_answer_core/LLM/LLMAdapter.py
smart_answer_core/LLM/LLMWrapper.py
smart_answer_core/LLM/LangchainAdapter.py
smart_answer_core/LLM/TogetherAdapter.py
smart_answer_core/LLM/gptqAdapter.py
smart_answer_core/tools/__init__.py
smart_answer_core/tools/common.py
smart_answer_core/tools/interoperability.py
smart_answer_core/tools/lifecycle.py
smart_answer_core-0.0.10.dist-info/LICENSE
smart_answer_core-0.0.10.dist-info/METADATA
smart_answer_core-0.0.10.dist-info/WHEEL
smart_answer_core-0.0.10.dist-info/entry_points.txt
smart_answer_core-0.0.10.dist-info/top_level.txt
smart_answer_core-0.0.10.dist-info/RECORD
